jkclient/__about__.py
jkclient/__init__.py
jkclient/client.py
jkclient/schema.py
jkclient/models/__init__.py
jkclient/models/v1_kernel.py
jkclient/models/v1_kernel_condition.py
jkclient/models/v1_kernel_spec.py
jkclient/models/v1_kernel_status.py
jkclient-0.0.7.dist-info/METADATA
jkclient-0.0.7.dist-info/WHEEL
jkclient-0.0.7.dist-info/licenses/LICENSE
jkclient-0.0.7.dist-info/RECORD
