Metadata-Version: 2.3
Name: jkclient
Version: 0.0.7
Summary: Kubernetes Jupyter Kernel CRD Client
Project-URL: Documentation, https://github.com/weekenthralling/jupyter-kernel-client#readme
Project-URL: Issues, https://github.com/weekenthralling/jupyter-kernel-client/issues
Project-URL: Source, https://github.com/weekenthralling/jupyter-kernel-client
Author-email: Mo Zhou <weekenthralling@gmail.com>
License-Expression: Apache-2.0
License-File: LICENSE
Classifier: Development Status :: 4 - Beta
Classifier: Programming Language :: Python
Classifier: Programming Language :: Python :: 3.8
Classifier: Programming Language :: Python :: 3.9
Classifier: Programming Language :: Python :: 3.10
Classifier: Programming Language :: Python :: 3.11
Classifier: Programming Language :: Python :: 3.12
Classifier: Programming Language :: Python :: Implementation :: CPython
Classifier: Programming Language :: Python :: Implementation :: PyPy
Requires-Python: >=3.8
Requires-Dist: kubernetes>=30
Requires-Dist: pydantic>=2
